package_calcular_porcentagem/__init__.py
package_calcular_porcentagem/format/__init__.py
package_calcular_porcentagem/format/output.py
package_calcular_porcentagem/utils/__init__.py
package_calcular_porcentagem/utils/calc_preco.py
package_calcular_porcentagem-0.0.1.dist-info/METADATA
package_calcular_porcentagem-0.0.1.dist-info/WHEEL
package_calcular_porcentagem-0.0.1.dist-info/top_level.txt
package_calcular_porcentagem-0.0.1.dist-info/RECORD
