Metadata-Version: 2.1
Name: package-calcular-porcentagem
Version: 0.0.1
Summary: The package is used for to calculate the porcentage in your code.
Home-page: https://github.com/Will-Moura
Author: WilliamMoura
Author-email: william_2207.moura@hotmail.com
License: UNKNOWN
Platform: UNKNOWN
Requires-Python: >=3.8
Requires-Dist: def
